certbot_dns_bunny/__init__.py
certbot_dns_bunny/py.typed
certbot_dns_bunny/_internal/__init__.py
certbot_dns_bunny/_internal/dns_bunny.py
certbot_dns_bunny-3.0.0.dist-info/LICENSE
certbot_dns_bunny-3.0.0.dist-info/METADATA
certbot_dns_bunny-3.0.0.dist-info/WHEEL
certbot_dns_bunny-3.0.0.dist-info/entry_points.txt
certbot_dns_bunny-3.0.0.dist-info/top_level.txt
certbot_dns_bunny-3.0.0.dist-info/RECORD
