Metadata-Version: 2.1
Name: certbot-dns-bunny
Version: 3.0.0
Summary: Bunny.net DNS Authenticator plugin for Certbot
Home-page: https://github.com/mwt/certbot-dns-bunny
Author: Matthew W. Thomas
Author-email: certbot-dns-bunny@mwt.me
License: BSD-2-Clause
Classifier: Development Status :: 5 - Production/Stable
Classifier: Environment :: Plugins
Classifier: Intended Audience :: System Administrators
Classifier: License :: OSI Approved :: BSD License
Classifier: Operating System :: POSIX :: Linux
Classifier: Programming Language :: Python
Classifier: Programming Language :: Python :: 3
Classifier: Programming Language :: Python :: 3.7
Classifier: Programming Language :: Python :: 3.8
Classifier: Programming Language :: Python :: 3.9
Classifier: Programming Language :: Python :: 3.10
Classifier: Topic :: Internet :: WWW/HTTP
Classifier: Topic :: Security
Classifier: Topic :: System :: Installation/Setup
Classifier: Topic :: System :: Networking
Classifier: Topic :: System :: Systems Administration
Classifier: Topic :: Utilities
Requires-Python: >=3.7
License-File: LICENSE
Requires-Dist: requests >=2.25.1
Requires-Dist: setuptools >=41.6.0
Requires-Dist: acme >=3.0.0
Requires-Dist: certbot >=3.0.0
Provides-Extra: docs
Requires-Dist: Sphinx >=1.0 ; extra == 'docs'
Requires-Dist: sphinx-rtd-theme ; extra == 'docs'
